experiments/__init__.py
experiments/read_blocks.py
experiments/read_star.py
sfftk/__init__.py
sfftk/sff.conf
sfftk/sff.py
sfftk/core/__init__.py
sfftk/core/configs.py
sfftk/core/parser.py
sfftk/core/prep.py
sfftk/core/print_tools.py
sfftk/core/utils.py
sfftk/formats/__init__.py
sfftk/formats/am.py
sfftk/formats/base.py
sfftk/formats/ilastik.py
sfftk/formats/map.py
sfftk/formats/mod.py
sfftk/formats/seg.py
sfftk/formats/star.py
sfftk/formats/stl.py
sfftk/formats/surf.py
sfftk/formats/survos.py
sfftk/notes/__init__.py
sfftk/notes/find.py
sfftk/notes/modify.py
sfftk/notes/view.py
sfftk/readers/__init__.py
sfftk/readers/amreader.py
sfftk/readers/ilastikreader.py
sfftk/readers/mapreader.py
sfftk/readers/modreader.py
sfftk/readers/segreader.py
sfftk/readers/starreader.py
sfftk/readers/stlreader.py
sfftk/readers/surfreader.py
sfftk/readers/survosreader.py
sfftk/schema/__init__.py
sfftk/schema/emdb_sff.py
sfftk/schema/v_0_5_8.py
sfftk/schema/v_0_6_0_a_2.py
sfftk/schema/v_0_6_0_a_3.py
sfftk/schema/v_0_6_0_a_4.py
sfftk/schema/v_0_7_0_dev_0.py
sfftk/test_data/__init__.py
sfftk/unittests/__init__.py
sfftk/unittests/test_core.py
sfftk/unittests/test_formats.py
sfftk/unittests/test_main.py
sfftk/unittests/test_notes.py
sfftk/unittests/test_readers.py
sfftk/unittests/test_schema.py
sfftk-0.10.3.dist-info/LICENSE
sfftk-0.10.3.dist-info/METADATA
sfftk-0.10.3.dist-info/WHEEL
sfftk-0.10.3.dist-info/entry_points.txt
sfftk-0.10.3.dist-info/top_level.txt
sfftk-0.10.3.dist-info/RECORD
