Metadata-Version: 2.1
Name: sfftk
Version: 0.10.3
Summary: Toolkit for working with EMDB-SFF and other segmentation file formats
Home-page: https://emdb-empiar.github.io/EMDB-SFF/
Author: Paul K. Korir, PhD
Author-email: pkorir@ebi.ac.uk, paul.korir@gmail.com
License: Apache License
Project-URL: Report Issues, https://github.com/emdb-empiar/sfftk/issues
Project-URL: Documentation, http://sfftk.readthedocs.io/en/latest/index.html
Project-URL: Souce Code, https://github.com/emdb-empiar/sfftk
Keywords: EMDB-SFF,SFF,segmentation
Platform: UNKNOWN
Classifier: Development Status :: 2 - Pre-Alpha
Classifier: Environment :: Console
Classifier: Intended Audience :: Developers
Classifier: Intended Audience :: Science/Research
Classifier: License :: OSI Approved :: Apache Software License
Classifier: Operating System :: OS Independent
Classifier: Programming Language :: Python :: 3
Classifier: Programming Language :: Python :: 3.7
Classifier: Programming Language :: Python :: 3.8
Classifier: Programming Language :: Python :: 3.9
Classifier: Programming Language :: Python :: 3.10
Classifier: Programming Language :: Python :: 3.11
Classifier: Topic :: Software Development :: Libraries :: Python Modules
Classifier: Topic :: Terminals
Classifier: Topic :: Text Processing
Classifier: Topic :: Text Processing :: Markup
Classifier: Topic :: Utilities
Requires-Python: >=3.7
Requires-Dist: sfftk-rw (>=0.8.1)
Requires-Dist: numpy
Requires-Dist: ahds
Requires-Dist: styled
Requires-Dist: mrcfile
Requires-Dist: bitarray
Requires-Dist: requests
Requires-Dist: mock
Requires-Dist: numpy-stl
Requires-Dist: gemmi
